Metadata-Version: 1.1
Name: fdic
Version: 0.1.3
Summary: Simple tools for accessing FDIC public data.
Home-page: http://github.com/aocks/fdic
Author: Emin Martinian
Author-email: emin.martinian@gmail.com
License: agpl-3.0
Keywords: fdic bank data tools
Platform: UNKNOWN
Classifier: Development Status :: 3 - Alpha
Classifier: Intended Audience :: Developers
Classifier: Programming Language :: Python :: 3
